[
    {
    "img": "https://ssl.gstatic.com/onebox/media/sports/logos/exZiFUT_GXScTyr358t7SQ_96x96.png",
    "name": "CSK Vs MI - 1ST APRIL",
    "link": "link",
    "index": "1"    
    "screen": "web"
    },
    {
    "img": "https://ssl.gstatic.com/onebox/media/sports/logos/exZiFUT_GXScTyr358t7SQ_96x96.png",
    "name": "CSK Vs MI - 1ST APRIL",
    "link": "link",
    "index": "2"    
    "screen": "web"
    },
    {
    "version": "0.01",
    "vlink": "link",
    "vdisc": "test",
    "hide": "1",
    "tellink": "link",
    "telname": "GET MATCH PREDICTION"   
    },
    {
    "version": "0.01",
    "vlink": "link",
    "vdisc": "test",	    
    "hide": "1",
    "tellink": "link",
    "telname": "GET MATCH PREDICTION"      
    }	
]    
